Workbook
Name TaxRate: Settings!$B$1

Sheet Summary
A1: Regional Sales Summary 2026
A2: Report date | B2: =DATE(2026,10,1) -> 46296 | D2: Opened | E2: =TODAY() -> 46302
A4: Region | B4: Q1 | C4: Q2 | D4: Q3 | E4: Q4 | F4: Total | G4: Share
A5: North | B5: =SUMIFS(Data!$F$2:$F$201,Data!$B$2:$B$201,$A5,Data!$A$2:$A$201,">="&DATE(2026,1,1),Data!$A$2:$A$201,"<"&DATE(2026,4,1)) -> 9521.25 | C5: =SUMIFS(Data!$F$2:$F$201,Data!$B$2:$B$201,$A5,Data!$A$2:$A$201,">="&DATE(2026,4,1),Data!$A$2:$A$201,"<"&DATE(2026,7,1)) -> 7775.25 | D5: =SUMIFS(Data!$F$2:$F$201,Data!$B$2:$B$201,$A5,Data!$A$2:$A$201,">="&DATE(2026,7,1),Data!$A$2:$A$201,"<"&DATE(2026,10,1)) -> 10733.75 | E5: =SUMIFS(Data!$F$2:$F$201,Data!$B$2:$B$201,$A5,Data!$A$2:$A$201,">="&DATE(2026,10,1),Data!$A$2:$A$201,"<"&DATE(2027,1,1)) -> 8329.25 | F5: =SUM(B5:E5) -> 36359.5 | G5: =F5/$F$9 -> 0.23023234
A6: South | B6: =SUMIFS(Data!$F$2:$F$201,Data!$B$2:$B$201,$A6,Data!$A$2:$A$201,">="&DATE(2026,1,1),Data!$A$2:$A$201,"<"&DATE(2026,4,1)) -> 6010 | C6: =SUMIFS(Data!$F$2:$F$201,Data!$B$2:$B$201,$A6,Data!$A$2:$A$201,">="&DATE(2026,4,1),Data!$A$2:$A$201,"<"&DATE(2026,7,1)) -> 10491.25 | D6: =SUMIFS(Data!$F$2:$F$201,Data!$B$2:$B$201,$A6,Data!$A$2:$A$201,">="&DATE(2026,7,1),Data!$A$2:$A$201,"<"&DATE(2026,10,1)) -> 10215 | E6: =SUMIFS(Data!$F$2:$F$201,Data!$B$2:$B$201,$A6,Data!$A$2:$A$201,">="&DATE(2026,10,1),Data!$A$2:$A$201,"<"&DATE(2027,1,1)) -> 15935 | F6: =SUM(B6:E6) -> 42651.25 | G6: =F6/$F$9 -> 0.27007239
A7: East | B7: =SUMIFS(Data!$F$2:$F$201,Data!$B$2:$B$201,$A7,Data!$A$2:$A$201,">="&DATE(2026,1,1),Data!$A$2:$A$201,"<"&DATE(2026,4,1)) -> 14424.5 | C7: =SUMIFS(Data!$F$2:$F$201,Data!$B$2:$B$201,$A7,Data!$A$2:$A$201,">="&DATE(2026,4,1),Data!$A$2:$A$201,"<"&DATE(2026,7,1)) -> 7887.25 | D7: =SUMIFS(Data!$F$2:$F$201,Data!$B$2:$B$201,$A7,Data!$A$2:$A$201,">="&DATE(2026,7,1),Data!$A$2:$A$201,"<"&DATE(2026,10,1)) -> 4681.25 | E7: =SUMIFS(Data!$F$2:$F$201,Data!$B$2:$B$201,$A7,Data!$A$2:$A$201,">="&DATE(2026,10,1),Data!$A$2:$A$201,"<"&DATE(2027,1,1)) -> 15319.25 | F7: =SUM(B7:E7) -> 42312.25 | G7: =F7/$F$9 -> 0.26792581
A8: West | B8: =SUMIFS(Data!$F$2:$F$201,Data!$B$2:$B$201,$A8,Data!$A$2:$A$201,">="&DATE(2026,1,1),Data!$A$2:$A$201,"<"&DATE(2026,4,1)) -> 8932.25 | C8: =SUMIFS(Data!$F$2:$F$201,Data!$B$2:$B$201,$A8,Data!$A$2:$A$201,">="&DATE(2026,4,1),Data!$A$2:$A$201,"<"&DATE(2026,7,1)) -> 8728.25 | D8: =SUMIFS(Data!$F$2:$F$201,Data!$B$2:$B$201,$A8,Data!$A$2:$A$201,">="&DATE(2026,7,1),Data!$A$2:$A$201,"<"&DATE(2026,10,1)) -> 4232.5 | E8: =SUMIFS(Data!$F$2:$F$201,Data!$B$2:$B$201,$A8,Data!$A$2:$A$201,">="&DATE(2026,10,1),Data!$A$2:$A$201,"<"&DATE(2027,1,1)) -> 14709.25 | F8: =SUM(B8:E8) -> 36602.25 | G8: =F8/$F$9 -> 0.23176946
A9: Total | B9: =SUM(B5:B8) -> 38888 | C9: =SUM(C5:C8) -> 34882 | D9: =SUM(D5:D8) -> 29862.5 | E9: =SUM(E5:E8) -> 54292.75 | F9: =SUM(F5:F8) -> 157925.25 | G9: =SUM(G5:G8) -> 1
A11: Tax rate | B11: =TaxRate -> 0.2
A12: Tax due | B12: =F9*TaxRate -> 31585.05
A13: Top region | B13: =INDEX(A5:A8,MATCH(MAX(F5:F8),F5:F8,0)) -> South
A14: Regions | B14: =_xlfn.TEXTJOIN(", ",TRUE,A5:A8) -> North, South, East, West
A15: Regions (CONCAT) | B15: =_xlfn.CONCAT(A5:A8) -> NorthSouthEastWest
A16: Margin (LET) | B16: =_xlfn.LET(revenue,F9,cost,F9*0.6,revenue-cost) -> 63170.1
A17: Margin after tax | B17: =B16*(1-TaxRate) -> 50536.08
A19: Sales handbook
A21: Month | B21: Revenue
A22: 46023 | B22: =SUMIFS(Data!$F$2:$F$201,Data!$A$2:$A$201,">="&A22,Data!$A$2:$A$201,"<"&EDATE(A22,1)) -> 12058.5
A23: 46054 | B23: =SUMIFS(Data!$F$2:$F$201,Data!$A$2:$A$201,">="&A23,Data!$A$2:$A$201,"<"&EDATE(A23,1)) -> 12862.25
A24: 46082 | B24: =SUMIFS(Data!$F$2:$F$201,Data!$A$2:$A$201,">="&A24,Data!$A$2:$A$201,"<"&EDATE(A24,1)) -> 13967.25
A25: 46113 | B25: =SUMIFS(Data!$F$2:$F$201,Data!$A$2:$A$201,">="&A25,Data!$A$2:$A$201,"<"&EDATE(A25,1)) -> 9803.25
A26: 46143 | B26: =SUMIFS(Data!$F$2:$F$201,Data!$A$2:$A$201,">="&A26,Data!$A$2:$A$201,"<"&EDATE(A26,1)) -> 13046.5
A27: 46174 | B27: =SUMIFS(Data!$F$2:$F$201,Data!$A$2:$A$201,">="&A27,Data!$A$2:$A$201,"<"&EDATE(A27,1)) -> 12032.25
A28: 46204 | B28: =SUMIFS(Data!$F$2:$F$201,Data!$A$2:$A$201,">="&A28,Data!$A$2:$A$201,"<"&EDATE(A28,1)) -> 10370.75
A29: 46235 | B29: =SUMIFS(Data!$F$2:$F$201,Data!$A$2:$A$201,">="&A29,Data!$A$2:$A$201,"<"&EDATE(A29,1)) -> 12110
A30: 46266 | B30: =SUMIFS(Data!$F$2:$F$201,Data!$A$2:$A$201,">="&A30,Data!$A$2:$A$201,"<"&EDATE(A30,1)) -> 7381.75
A31: 46296 | B31: =SUMIFS(Data!$F$2:$F$201,Data!$A$2:$A$201,">="&A31,Data!$A$2:$A$201,"<"&EDATE(A31,1)) -> 18863
A32: 46327 | B32: =SUMIFS(Data!$F$2:$F$201,Data!$A$2:$A$201,">="&A32,Data!$A$2:$A$201,"<"&EDATE(A32,1)) -> 17171
A33: 46357 | B33: =SUMIFS(Data!$F$2:$F$201,Data!$A$2:$A$201,">="&A33,Data!$A$2:$A$201,"<"&EDATE(A33,1)) -> 18258.75

Sheet Data
A1: Date | B1: Region | C1: Product | D1: Units | E1: Price | F1: Revenue
A2: 46023 | B2: North | C2: Widget | D2: 95 | E2: 12.5 | F2: =D2*E2 -> 1187.5
A3: 46024 | B3: East | C3: Widget | D3: 29 | E3: 12.5 | F3: =D3*E3 -> 362.5
A4: 46026 | B4: South | C4: Gizmo | D4: 14 | E4: 7.25 | F4: =D4*E4 -> 101.5
A5: 46028 | B5: North | C5: Gizmo | D5: 55 | E5: 7.25 | F5: =D5*E5 -> 398.75
A6: 46030 | B6: North | C6: Widget | D6: 12 | E6: 12.5 | F6: =D6*E6 -> 150
A7: 46032 | B7: South | C7: Widget | D7: 65 | E7: 12.5 | F7: =D7*E7 -> 812.5
A8: 46033 | B8: North | C8: Gizmo | D8: 26 | E8: 7.25 | F8: =D8*E8 -> 188.5
A9: 46035 | B9: West | C9: Widget | D9: 58 | E9: 12.5 | F9: =D9*E9 -> 725
A10: 46037 | B10: East | C10: Widget | D10: 98 | E10: 12.5 | F10: =D10*E10 -> 1225
A11: 46039 | B11: South | C11: Gizmo | D11: 55 | E11: 7.25 | F11: =D11*E11 -> 398.75
A12: 46041 | B12: East | C12: Gadget | D12: 20 | E12: 30 | F12: =D12*E12 -> 600
A13: 46043 | B13: South | C13: Gadget | D13: 14 | E13: 30 | F13: =D13*E13 -> 420
... A201: 46385 | B201: West | C201: Gizmo | D201: 31 | E201: 7.25 | F201: =D201*E201 -> 224.75

Sheet Lookups
A1: Lookup and formula examples
A3: Product | B3: Price (XLOOKUP) | C3: Price (VLOOKUP) | D3: Units sold (SUMIF) | F3: Product | G3: Price
A4: Widget | B4: {=_xlfn.XLOOKUP(A4,$F$4:$F$6,$G$4:$G$6)} -> 12.5 | C4: =VLOOKUP(A4,$F$4:$G$6,2,FALSE) -> 12.5 | D4: =SUMIF(Data!$C$2:$C$201,A4,Data!$D$2:$D$201) -> 4085 | F4: Widget | G4: 12.5
A5: Gadget | B5: {=_xlfn.XLOOKUP(A5,$F$4:$F$6,$G$4:$G$6)} -> 30 | C5: =VLOOKUP(A5,$F$4:$G$6,2,FALSE) -> 30 | D5: =SUMIF(Data!$C$2:$C$201,A5,Data!$D$2:$D$201) -> 2644 | F5: Gadget | G5: 30
A6: Gizmo | B6: {=_xlfn.XLOOKUP(A6,$F$4:$F$6,$G$4:$G$6)} -> 7.25 | C6: =VLOOKUP(A6,$F$4:$G$6,2,FALSE) -> 7.25 | D6: =SUMIF(Data!$C$2:$C$201,A6,Data!$D$2:$D$201) -> 3799 | F6: Gizmo | G6: 7.25
A8: Revenue (table reference) | B8: =SUM(SalesData[Revenue]) -> 157925.25
A9: Distinct regions (spill) | B9: {=_xlfn._xlws.SORT(_xlfn.UNIQUE(Data!B2:B201))} -> East
B10: North
B11: South
B12: West
A14: Weighted units (array) | B14: {=SUM(Data!D2:D201*Data!E2:E201)} -> 157925.25
A15: Doubled prices (array) | B15: {=TRANSPOSE(G4:G6*2)} -> 25 | C15: 60 | D15: 14.5
A17: Rich text | B17: Bold and italic text
A18: Price band (IFS) | B18: =_xlfn.IFS(B4>20,"High",B4>10,"Mid",TRUE,"Low") -> Mid
A19: Month end (EDATE) | B19: =EDATE(DATE(2026,1,31),1) -> 46081
A20: Label (text functions) | B20: =UPPER(LEFT(A4,3))&"-"&TEXT(G4,"0.00") -> WID-12.50
A21: Negative check | B21: =IF(SUM(D4:D6)<0,"Negative","OK") -> OK

Sheet Notes
A1: Notes
A2: This sheet holds a picture, a text box, hidden rows and sparklines. The editor keeps all of them when it saves, even though it only shows placeholders.
A6: Hidden | B6: row | C6: one
A7: Hidden | B7: row | C7: two
A9: Trend | B9: Jan | C9: Feb | D9: Mar | E9: Apr | F9: May
A10: Units | B10: 12 | C10: 18 | D10: 9 | E10: 24 | F10: 30

Sheet Reference
A1: Code | B1: Meaning
A2: N | B2: North
A3: S | B3: South
A4: E | B4: East
A5: W | B5: West

Sheet Settings
A1: Tax rate | B1: 0.2
